{
  "main": {
    "id": "774fba5771e1a017",
    "type": "split",
    "children": [
      {
        "id": "9cf6768db4b1eb7d",
        "type": "tabs",
        "children": [
          {
            "id": "5b5dc19eb9bf2682",
            "type": "leaf",
            "state": {
              "type": "markdown",
              "state": {
                "file": "origin/微信聊天，建议你冷淡一点.md",
                "mode": "source",
                "source": false
              }
            }
          }
        ]
      }
    ],
    "direction": "vertical"
  },
  "left": {
    "id": "1128291490e3e5f4",
    "type": "split",
    "children": [
      {
        "id": "8c1f2ff9ffb94953",
        "type": "tabs",
        "children": [
          {
            "id": "b2a2cbf87b07df11",
            "type": "leaf",
            "state": {
              "type": "file-explorer",
              "state": {
                "sortOrder": "alphabetical"
              }
            }
          },
          {
            "id": "729a5db1d8b89ae3",
            "type": "leaf",
            "state": {
              "type": "search",
              "state": {
                "query": "",
                "matchingCase": false,
                "explainSearch": false,
                "collapseAll": false,
                "extraContext": false,
                "sortOrder": "alphabetical"
              }
            }
          },
          {
            "id": "374f99a3a14c0c91",
            "type": "leaf",
            "state": {
              "type": "bookmarks",
              "state": {}
            }
          }
        ]
      }
    ],
    "direction": "horizontal",
    "width": 300
  },
  "right": {
    "id": "b511b72e4c964461",
    "type": "split",
    "children": [
      {
        "id": "9d1f1555faf7ee37",
        "type": "tabs",
        "children": [
          {
            "id": "3940a57db3795d16",
            "type": "leaf",
            "state": {
              "type": "backlink",
              "state": {
                "file": "origin/微信聊天，建议你冷淡一点.md",
                "collapseAll": false,
                "extraContext": false,
                "sortOrder": "alphabetical",
                "showSearch": false,
                "searchQuery": "",
                "backlinkCollapsed": false,
                "unlinkedCollapsed": true
              }
            }
          },
          {
            "id": "d39c79b6671b8371",
            "type": "leaf",
            "state": {
              "type": "outgoing-link",
              "state": {
                "file": "origin/微信聊天，建议你冷淡一点.md",
                "linksCollapsed": false,
                "unlinkedCollapsed": true
              }
            }
          },
          {
            "id": "537b0dd852ffacd9",
            "type": "leaf",
            "state": {
              "type": "tag",
              "state": {
                "sortOrder": "frequency",
                "useHierarchy": true
              }
            }
          },
          {
            "id": "31db2c833ec3f2d5",
            "type": "leaf",
            "state": {
              "type": "outline",
              "state": {
                "file": "origin/微信聊天，建议你冷淡一点.md"
              }
            }
          }
        ]
      }
    ],
    "direction": "horizontal",
    "width": 300,
    "collapsed": true
  },
  "left-ribbon": {
    "hiddenItems": {
      "switcher:打开快速切换": false,
      "graph:查看关系图谱": false,
      "canvas:新建白板": false,
      "daily-notes:打开/创建今天的日记": false,
      "templates:插入模板": false,
      "command-palette:打开命令面板": false
    }
  },
  "active": "5b5dc19eb9bf2682",
  "lastOpenFiles": [
    "information/职场.md",
    "origin/为什么不取消日报、周报.md",
    "origin/微信聊天，建议你冷淡一点.md",
    "origin/停止内耗，你的人生就顺了.md",
    "origin/太累后，如何快速复原？.md",
    "origin/思路混乱的人，一人拖垮一个团队.md",
    "origin/说话「阴阳怪气」的人，如何回击？.md",
    "origin/深度学习的4个底层逻辑.md",
    "origin/如何做到自我接纳？.md",
    "origin/如何自我激励？.md",
    "origin/如何让自己更有配得感？.md",
    "origin/如何每天只睡6小时，依然精力充沛？.md",
    "origin/情绪急救的6个小方法.md",
    "origin/情感氪石.md",
    "information/健康.md",
    "origin/为什么你的新年目标通常都很难完成.md",
    "origin/为什么你总是越睡越困.md",
    "origin/我从成功人士身上「偷」来的12件事.md",
    "information/成长.md",
    "information/情感.md",
    "origin/健康的自私非常必要.md",
    "origin/健康关系的6个特点.md",
    "origin/为什么我们总是觉得学习很难？.md",
    "origin/为什么越理性的人越软弱？.md",
    "information/社会.md",
    "origin/建立人脉.md"
  ]
}